martialaw/__init__.py
martialaw/martialaw.py
martialaw-0.0.1.dist-info/LICENSE
martialaw-0.0.1.dist-info/METADATA
martialaw-0.0.1.dist-info/WHEEL
martialaw-0.0.1.dist-info/top_level.txt
martialaw-0.0.1.dist-info/RECORD
